soliscloud/__init__.py
soliscloud/soliscloud.py
soliscloud-1.1.2.dist-info/licenses/LICENSE
soliscloud-1.1.2.dist-info/METADATA
soliscloud-1.1.2.dist-info/WHEEL
soliscloud-1.1.2.dist-info/top_level.txt
soliscloud-1.1.2.dist-info/RECORD
