Metadata-Version: 2.4
Name: soliscloud
Version: 1.1.2
Summary: A small package to work with Solis Cloud API
Home-page: https://github.com/skywatcher-uk/soliscloud
Author: Skywatcher
Author-email: integrations@skywatcher.uk
Classifier: Programming Language :: Python :: 3
Classifier: License :: OSI Approved :: MIT License
Classifier: Operating System :: OS Independent
License-File: LICENSE
Requires-Dist: requests
Requires-Dist: tenacity
Dynamic: author
Dynamic: author-email
Dynamic: classifier
Dynamic: description
Dynamic: description-content-type
Dynamic: home-page
Dynamic: license-file
Dynamic: requires-dist
Dynamic: summary
